eodag/__init__.py
eodag/cli.py
eodag/config.py
eodag/crunch.py
eodag/py.typed
eodag/api/__init__.py
eodag/api/core.py
eodag/api/search_result.py
eodag/api/product/__init__.py
eodag/api/product/_assets.py
eodag/api/product/_product.py
eodag/api/product/metadata_mapping.py
eodag/api/product/drivers/__init__.py
eodag/api/product/drivers/base.py
eodag/api/product/drivers/generic.py
eodag/api/product/drivers/sentinel1.py
eodag/api/product/drivers/sentinel2.py
eodag/plugins/__init__.py
eodag/plugins/base.py
eodag/plugins/manager.py
eodag/plugins/apis/__init__.py
eodag/plugins/apis/base.py
eodag/plugins/apis/ecmwf.py
eodag/plugins/apis/usgs.py
eodag/plugins/authentication/__init__.py
eodag/plugins/authentication/aws_auth.py
eodag/plugins/authentication/base.py
eodag/plugins/authentication/generic.py
eodag/plugins/authentication/header.py
eodag/plugins/authentication/keycloak.py
eodag/plugins/authentication/oauth.py
eodag/plugins/authentication/openid_connect.py
eodag/plugins/authentication/qsauth.py
eodag/plugins/authentication/sas_auth.py
eodag/plugins/authentication/token.py
eodag/plugins/authentication/token_exchange.py
eodag/plugins/crunch/__init__.py
eodag/plugins/crunch/base.py
eodag/plugins/crunch/filter_date.py
eodag/plugins/crunch/filter_latest_intersect.py
eodag/plugins/crunch/filter_latest_tpl_name.py
eodag/plugins/crunch/filter_overlap.py
eodag/plugins/crunch/filter_property.py
eodag/plugins/download/__init__.py
eodag/plugins/download/aws.py
eodag/plugins/download/base.py
eodag/plugins/download/creodias_s3.py
eodag/plugins/download/http.py
eodag/plugins/download/s3rest.py
eodag/plugins/search/__init__.py
eodag/plugins/search/base.py
eodag/plugins/search/build_search_result.py
eodag/plugins/search/cop_marine.py
eodag/plugins/search/creodias_s3.py
eodag/plugins/search/csw.py
eodag/plugins/search/data_request_search.py
eodag/plugins/search/qssearch.py
eodag/plugins/search/stac_list_assets.py
eodag/plugins/search/static_stac_search.py
eodag-3.10.1.dist-info/licenses/LICENSE
eodag-3.10.1.dist-info/METADATA
eodag-3.10.1.dist-info/WHEEL
eodag-3.10.1.dist-info/entry_points.txt
eodag-3.10.1.dist-info/top_level.txt
eodag-3.10.1.dist-info/RECORD
