Metadata-Version: 2.4
Name: eodag
Version: 3.10.1
Summary: Earth Observation Data Access Gateway
Home-page: https://github.com/CS-SI/eodag
Author: CS GROUP - France
Author-email: eodag@csgroup.space
License: Apache 2.0
Project-URL: Bug Tracker, https://github.com/CS-SI/eodag/issues/
Project-URL: Documentation, https://eodag.readthedocs.io
Project-URL: Source Code, https://github.com/CS-SI/eodag
Classifier: Development Status :: 5 - Production/Stable
Classifier: Intended Audience :: Developers
Classifier: Intended Audience :: Science/Research
Classifier: Natural Language :: English
Classifier: License :: OSI Approved :: Apache Software License
Classifier: Operating System :: Microsoft :: Windows
Classifier: Operating System :: POSIX :: Linux
Classifier: Programming Language :: Python
Classifier: Programming Language :: Python :: 3
Classifier: Programming Language :: Python :: 3.9
Classifier: Programming Language :: Python :: 3.10
Classifier: Programming Language :: Python :: 3.11
Classifier: Programming Language :: Python :: 3.12
Classifier: Programming Language :: Python :: 3.13
Classifier: Programming Language :: Python :: 3.14
Classifier: Programming Language :: Python :: Implementation :: CPython
Classifier: Topic :: Internet :: WWW/HTTP :: Indexing/Search
Classifier: Topic :: Scientific/Engineering :: GIS
Classifier: Topic :: Software Development :: Libraries :: Python Modules
Classifier: Typing :: Typed
Requires-Python: >=3.6
License-File: LICENSE
Requires-Dist: annotated-types
Requires-Dist: boto3
Requires-Dist: botocore
Requires-Dist: click
Requires-Dist: geojson
Requires-Dist: importlib_metadata>=5.0
Requires-Dist: jsonpath-ng
Requires-Dist: lxml
Requires-Dist: orjson
Requires-Dist: pydantic!=2.10.0,>=2.1.0
Requires-Dist: pydantic_core
Requires-Dist: PyJWT[crypto]>=2.5.0
Requires-Dist: pyproj>=2.1.0
Requires-Dist: pyshp
Requires-Dist: pystac>=1.0.0b1
Requires-Dist: python-dateutil
Requires-Dist: PyYAML
Requires-Dist: requests
Requires-Dist: shapely>=2.0.6
Requires-Dist: tqdm
Requires-Dist: typing_extensions>=4.8.0
Requires-Dist: urllib3
Requires-Dist: zipstream-ng
Provides-Extra: all
Requires-Dist: eodag[all-providers,csw,server,tutorials]; extra == "all"
Provides-Extra: all-providers
Requires-Dist: eodag[ecmwf,usgs]; extra == "all-providers"
Provides-Extra: csw
Requires-Dist: OWSLib>=0.27.1; extra == "csw"
Provides-Extra: ecmwf
Requires-Dist: ecmwf-api-client; extra == "ecmwf"
Provides-Extra: usgs
Requires-Dist: usgs>=0.3.6; extra == "usgs"
Provides-Extra: server
Requires-Dist: fastapi>=0.93.0; extra == "server"
Requires-Dist: pygeofilter; extra == "server"
Requires-Dist: starlette; extra == "server"
Requires-Dist: uvicorn[standard]; extra == "server"
Requires-Dist: pydantic-settings; extra == "server"
Requires-Dist: cachetools; extra == "server"
Provides-Extra: notebook
Requires-Dist: tqdm[notebook]; extra == "notebook"
Provides-Extra: tutorials
Requires-Dist: eodag[ecmwf,notebook]; extra == "tutorials"
Requires-Dist: eodag-cube>=0.6.0b2; extra == "tutorials"
Requires-Dist: jupyter; extra == "tutorials"
Requires-Dist: ipyleaflet>=0.10.0; extra == "tutorials"
Requires-Dist: ipywidgets; extra == "tutorials"
Requires-Dist: matplotlib; extra == "tutorials"
Requires-Dist: folium; extra == "tutorials"
Requires-Dist: imageio; extra == "tutorials"
Requires-Dist: rasterio; extra == "tutorials"
Requires-Dist: netcdf4; extra == "tutorials"
Requires-Dist: cartopy; extra == "tutorials"
Requires-Dist: covjsonkit; extra == "tutorials"
Provides-Extra: dev
Requires-Dist: eodag[all-providers,csw,server,stubs]; extra == "dev"
Requires-Dist: pytest; extra == "dev"
Requires-Dist: pytest-cov; extra == "dev"
Requires-Dist: py>=1.8.2; extra == "dev"
Requires-Dist: pytest-html!=3.2.0; extra == "dev"
Requires-Dist: pytest-xdist; extra == "dev"
Requires-Dist: pytest-socket; extra == "dev"
Requires-Dist: pytest-instafail; extra == "dev"
Requires-Dist: tox; extra == "dev"
Requires-Dist: tox-uv; extra == "dev"
Requires-Dist: faker; extra == "dev"
Requires-Dist: moto>=5; extra == "dev"
Requires-Dist: twine; extra == "dev"
Requires-Dist: wheel; extra == "dev"
Requires-Dist: flake8; extra == "dev"
Requires-Dist: pre-commit; extra == "dev"
Requires-Dist: responses!=0.24.0; extra == "dev"
Requires-Dist: fastapi[all]; extra == "dev"
Requires-Dist: stdlib-list; extra == "dev"
Requires-Dist: mypy; extra == "dev"
Provides-Extra: stubs
Requires-Dist: boto3-stubs[essential]; extra == "stubs"
Requires-Dist: types-lxml; extra == "stubs"
Requires-Dist: types-cachetools; extra == "stubs"
Requires-Dist: types-requests; extra == "stubs"
Requires-Dist: types-python-dateutil; extra == "stubs"
Requires-Dist: types-PyYAML; extra == "stubs"
Requires-Dist: types-setuptools; extra == "stubs"
Requires-Dist: types-shapely; extra == "stubs"
Requires-Dist: types-tqdm; extra == "stubs"
Requires-Dist: types-urllib3; extra == "stubs"
Provides-Extra: docs
Requires-Dist: eodag[all,stubs]; extra == "docs"
Requires-Dist: nbsphinx; extra == "docs"
Requires-Dist: sphinx; extra == "docs"
Requires-Dist: sphinx-autodoc-typehints; extra == "docs"
Requires-Dist: sphinx-book-theme>=1.0.0; extra == "docs"
Requires-Dist: sphinx-copybutton; extra == "docs"
Requires-Dist: sphinx-design; extra == "docs"
Requires-Dist: sphinx-tabs; extra == "docs"
Requires-Dist: sphinxcontrib-programoutput; extra == "docs"
Requires-Dist: sphinxemoji; extra == "docs"
Dynamic: license-file
